GDR/__init__.py
GDR/dim_reduce_dataset.py
GDR/experiment_utils/__init__.py
GDR/experiment_utils/decorator_rapids.py
GDR/experiment_utils/general_utils.py
GDR/experiment_utils/get_algorithm.py
GDR/experiment_utils/get_data.py
GDR/experiment_utils/grad_analysis.py
GDR/nndescent/__init__.py
GDR/nndescent/setup.py
GDR/nndescent/py_files/__init__.py
GDR/nndescent/py_files/distances.py
GDR/nndescent/py_files/pynndescent_.py
GDR/nndescent/py_files/rp_trees.py
GDR/nndescent/py_files/utils.py
GDR/optimizer/GradientDR.py
GDR/optimizer/__init__.py
GDR/optimizer/distances.py
GDR/optimizer/graph_weights.py
GDR/optimizer/pytorch_optimize.py
GDR/optimizer/spectral.py
GDR/optimizer/utils.py
GDR/optimizer/numba_optimizers/__init__.py
GDR/optimizer/numba_optimizers/gdr.py
GDR/optimizer/numba_optimizers/numba_utils.py
GDR/optimizer/numba_optimizers/umap.py
GradientDR-0.1.3.4.dist-info/LICENSE
GradientDR-0.1.3.4.dist-info/METADATA
GradientDR-0.1.3.4.dist-info/WHEEL
GradientDR-0.1.3.4.dist-info/top_level.txt
GradientDR-0.1.3.4.dist-info/RECORD
